funlib/persistence/__init__.py
funlib/persistence/py.typed
funlib/persistence/types.py
funlib/persistence/arrays/__init__.py
funlib/persistence/arrays/array.py
funlib/persistence/arrays/datasets.py
funlib/persistence/arrays/freezable.py
funlib/persistence/arrays/lazy_ops.py
funlib/persistence/arrays/metadata.py
funlib/persistence/arrays/ome_datasets.py
funlib/persistence/arrays/utils.py
funlib/persistence/graphs/__init__.py
funlib/persistence/graphs/graph_database.py
funlib/persistence/graphs/pgsql_graph_database.py
funlib/persistence/graphs/sql_graph_database.py
funlib/persistence/graphs/sqlite_graph_database.py
funlib_persistence-0.6.1.dist-info/licenses/LICENSE
funlib_persistence-0.6.1.dist-info/METADATA
funlib_persistence-0.6.1.dist-info/WHEEL
funlib_persistence-0.6.1.dist-info/top_level.txt
funlib_persistence-0.6.1.dist-info/RECORD
